python_wsmanclient-0.1.0.dist-info/DESCRIPTION.rst
python_wsmanclient-0.1.0.dist-info/METADATA
python_wsmanclient-0.1.0.dist-info/RECORD
python_wsmanclient-0.1.0.dist-info/WHEEL
python_wsmanclient-0.1.0.dist-info/metadata.json
python_wsmanclient-0.1.0.dist-info/pbr.json
python_wsmanclient-0.1.0.dist-info/top_level.txt
wsmanclient/__init__.py
wsmanclient/client.py
wsmanclient/exceptions.py
wsmanclient/version.py
wsmanclient/tests/__init__.py
wsmanclient/tests/test_client.py
wsmanclient/tests/utils.py
wsmanclient/tests/wsman_mocks/wsman-enum_context-1.xml
wsmanclient/tests/wsman_mocks/wsman-enum_context-2.xml
wsmanclient/tests/wsman_mocks/wsman-enum_context-3.xml
wsmanclient/tests/wsman_mocks/wsman-enum_context-4.xml
