Metadata-Version: 2.0
Name: python-wsmanclient
Version: 0.1.0
Summary: Python client that speaks Web Services-Management protocol
Home-page: https://launchpad.net/python-wsmanclient
Author: Imre Farkas
Author-email: ifarkas@redhat.com
License: Apache-2
Platform: UNKNOWN
Classifier: Development Status :: 3 - Alpha
Classifier: Environment :: OpenStack
Classifier: Intended Audience :: System Administrators
Classifier: License :: OSI Approved :: Apache Software License
Classifier: Operating System :: POSIX
Classifier: Programming Language :: Python
Classifier: Programming Language :: Python :: 2
Classifier: Programming Language :: Python :: 2.7
Classifier: Programming Language :: Python :: 3
Classifier: Programming Language :: Python :: 3.4
Requires-Dist: lxml (>=2.3)
Requires-Dist: pbr (>=1.6)
Requires-Dist: requests (>=2.5.2)
